fastapi_explosion_extras/__init__.py
fastapi_explosion_extras/initialize.py
fastapi_explosion_extras/logs.py
fastapi_explosion_extras/routing.py
fastapi_explosion_extras/types.py
fastapi_explosion_extras/tests/__init__.py
fastapi_explosion_extras/tests/api.py
fastapi_explosion_extras/tests/test_init_app.py
fastapi_explosion_extras/tests/test_router.py
fastapi_explosion_extras-0.4.0.dist-info/METADATA
fastapi_explosion_extras-0.4.0.dist-info/WHEEL
fastapi_explosion_extras-0.4.0.dist-info/top_level.txt
fastapi_explosion_extras-0.4.0.dist-info/zip-safe
fastapi_explosion_extras-0.4.0.dist-info/RECORD
